{"ValueSet":{"text":{"status":{"value":"generated"},"div":"<div><h2>FamilialRelationship<\/h2><p>The nature of the relationship between the patient and the person with the condition. Based on the HL7v3 RoleCode: OID: 2.16.840.1.113883.5.111 with some inappropriate items removed<\/p><p>This value set includes codes defined in other code systems, using the following rules:<\/p><ul><li>Include these codes as defined in <a href=\"http://hl7.org/fhir/v3/RoleCode\">http://hl7.org/fhir/v3/RoleCode<\/a><table><tr><td><b>Code<\/b><\/td><td><b>Display<\/b><\/td><td><b>Definition<\/b><\/td><\/tr><tr><td>AUNT<\/td><td>aunt<\/td><td>The player of the role is a sister of the scoping person's mother or father.<\/td><\/tr><tr><td>BRO<\/td><td>Brother<\/td><td>The player of the role is a male sharing one or both parents in common with the scoping entity.<\/td><\/tr><tr><td>BROINLAW<\/td><td>brother-in-law<\/td><td>The player of the role is: (1) a brother of the scoping person's spouse, or (2) the husband of the scoping person's sister, or (3) the husband of a sister of the scoping person's spouse.<\/td><\/tr><tr><td>CHLDADOPT<\/td><td>adopted child<\/td><td>The player of the role is a child taken into a family through legal means and raised by the scoping person (parent) as his or her own child.<\/td><\/tr><tr><td>CHLDFOST<\/td><td>foster child<\/td><td>The player of the role is a child receiving parental care and nurture from the scoping person (parent) but not related to him or her through legal or blood ties.<\/td><\/tr><tr><td>CHLDINLAW<\/td><td>child in-law<\/td><td>The player of the role is the spouse of scoping person's child.<\/td><\/tr><tr><td>COUSN<\/td><td>cousin<\/td><td>The player of the role is a relative of the scoping person descended from a common ancestor, such as a grandparent, by two or more steps in a diverging line.<\/td><\/tr><tr><td>DAU<\/td><td>natural daughter<\/td><td>The player of the role is a female offspring of the scoping entity (parent).<\/td><\/tr><tr><td>DAUADOPT<\/td><td>adopted daughter<\/td><td>The player of the role is a female child taken into a family through legal means and raised by the scoping person (parent) as his or her own child.<\/td><\/tr><tr><td>DAUC<\/td><td>Daughter<\/td><td>&lt;New Concept&gt; The player of the role is a female child (of any type) of scoping entity (parent).<\/td><\/tr><tr><td>DAUFOST<\/td><td>foster daughter<\/td><td>The player of the role is a female child receiving parental care and nurture from the scoping person (parent) but not related to him or her through legal or blood ties.<\/td><\/tr><tr><td>DAUINLAW<\/td><td>daughter in-law<\/td><td>The player of the role is the wife of scoping person's son.<\/td><\/tr><tr><td>CHILD<\/td><td>Child<\/td><td>The player of the role is a child of the scoping entity.<\/td><\/tr><tr><td>EXT<\/td><td>extended family member<\/td><td>A family member outside the immediate family unit, not having a direct genetic or legal relationship e.g. Aunt, cousin, great grandparent, grandchild, grandparent, neiceNephew, and uncle.<\/td><\/tr><tr><td>IMED<\/td><td/><td>A member of the immediate family unit by direct genetic or legal relationship.<\/td><\/tr><tr><td>PRN<\/td><td>Parent<\/td><td>one that begets or brings forth offspring or a person who brings up and cares for another (Webster's Collegiate Dictionary).<\/td><\/tr><tr><td>SIB<\/td><td>Sibling<\/td><td>One person who shares a parent or parents with another.<\/td><\/tr><tr><td>SIGOTHR<\/td><td>significant other<\/td><td>A person who is important to one's well being; especially a spouse or one in a similar relationship. (The player is the one who is important).<\/td><\/tr><tr><td>DOMPART<\/td><td>domestic partner<\/td><td>The player of the role cohabits with the scoping person but is not the scoping person's spouse.<\/td><\/tr><tr><td>SPS<\/td><td>spouse<\/td><td>The player of the role is a marriage partner of the scoping person.<\/td><\/tr><tr><td>FTH<\/td><td>Father<\/td><td>The player of the role is a male who begets or raises or nurtures the scoping entity (child).<\/td><\/tr><tr><td>FTHINLAW<\/td><td>father-in-law<\/td><td>The player of the role is the father of the scoping person's husband or wife.<\/td><\/tr><tr><td>GGRFTH<\/td><td>great grandfather<\/td><td>The player of the role is the father of the scoping person's grandparent.<\/td><\/tr><tr><td>GGRMTH<\/td><td>great grandmother<\/td><td>The player of the role is the mother of the scoping person's grandparent.<\/td><\/tr><tr><td>GGRPRN<\/td><td>great grandparent<\/td><td>The player of the role is a parent of the scoping person's grandparent.<\/td><\/tr><tr><td>GRFTH<\/td><td>Grandfather<\/td><td>The player of the role is the father of the scoping person's mother or father.<\/td><\/tr><tr><td>GRMTH<\/td><td>Grandmother<\/td><td>The player of the role is the mother of the scoping person's mother or father.<\/td><\/tr><tr><td>GRNDCHILD<\/td><td>grandchild<\/td><td>The player of the role is a child of the scoping person's son or daughter.<\/td><\/tr><tr><td>GRNDDAU<\/td><td>granddaughter<\/td><td>The player of the role is a daughter of the scoping person's son or daughter.<\/td><\/tr><tr><td>GRNDSON<\/td><td>grandson<\/td><td>The player of the role is a son of the scoping person's son or daughter.<\/td><\/tr><tr><td>GRPRN<\/td><td>Grandparent<\/td><td>parent of a parent of the subject.<\/td><\/tr><tr><td>HBRO<\/td><td>half-brother<\/td><td>The player of the role is a male related to the scoping entity by sharing only one biological parent.<\/td><\/tr><tr><td>HSIB<\/td><td>half-sibling<\/td><td>The player of the role is related to the scoping entity by sharing only one biological parent.<\/td><\/tr><tr><td>HSIS<\/td><td>half-sister<\/td><td>The player of the role is a female related to the scoping entity by sharing only one biological parent.<\/td><\/tr><tr><td>HUSB<\/td><td>husband<\/td><td>The player of the role is a man joined to a woman (scoping person) in marriage.<\/td><\/tr><tr><td>MTH<\/td><td>Mother<\/td><td>The player of the role is a female who conceives, gives birth to, or raises and nurtures the scoping entity (child).<\/td><\/tr><tr><td>MTHINLAW<\/td><td>mother-in-law<\/td><td>The player of the role is the mother of the scoping person's husband or wife.<\/td><\/tr><tr><td>NBOR<\/td><td>neighbor<\/td><td>The player of the role lives near or next to the scoping person.<\/td><\/tr><tr><td>NBRO<\/td><td>natural brother<\/td><td>The player of the role is a male having the same biological parents as the scoping entity.<\/td><\/tr><tr><td>NCHILD<\/td><td>natural child<\/td><td>A child as determined by birth.<\/td><\/tr><tr><td>NEPHEW<\/td><td>nephew<\/td><td>The player of the role is a son of the scoping person's brother or sister or of the brother or sister of the scoping person's spouse.<\/td><\/tr><tr><td>NFTH<\/td><td>natural father<\/td><td>The player of the role is a male who begets the scoping entity (child).<\/td><\/tr><tr><td>NFTHF<\/td><td>natural father of fetus<\/td><td>Indicates the biologic male parent of a fetus.<\/td><\/tr><tr><td>NIECE<\/td><td>niece<\/td><td>The player of the role is a daughter of the scoping person's brother or sister or of the brother or sister of the scoping person's spouse.<\/td><\/tr><tr><td>NIENEPH<\/td><td>niece/nephew<\/td><td>The player of the role is a child of scoping person's brother or sister or of the brother or sister of the scoping person's spouse.<\/td><\/tr><tr><td>NMTH<\/td><td>natural mother<\/td><td>The player of the role is a female who conceives or gives birth to the scoping entity (child).<\/td><\/tr><tr><td>NOK<\/td><td>next of kin<\/td><td>Played by an individual who is designated as the next of kin for another individual which scopes the role.<\/td><\/tr><tr><td>NPRN<\/td><td>natural parent<\/td><td/><\/tr><tr><td>NSIB<\/td><td>natural sibling<\/td><td>The player of the role has both biological parents in common with the scoping entity.<\/td><\/tr><tr><td>NSIS<\/td><td>natural sister<\/td><td>The player of the role is a female having the same biological parents as the scoping entity.<\/td><\/tr><tr><td>PRNINLAW<\/td><td>parent in-law<\/td><td>The player of the role is the parent of scoping person's husband or wife.<\/td><\/tr><tr><td>ROOM<\/td><td>Roommate<\/td><td>One who shares living quarters with the subject.<\/td><\/tr><tr><td>SIBINLAW<\/td><td>sibling in-law<\/td><td>The player of the role is: (1) a sibling of the scoping person's spouse, or (2) the spouse of the scoping person's sibling, or (3) the spouse of a sibling of the scoping person's spouse.<\/td><\/tr><tr><td>SIS<\/td><td>Sister<\/td><td>The player of the role is a female sharing one or both parents in common with the scoping entity.<\/td><\/tr><tr><td>SISINLAW<\/td><td>sister-in-law<\/td><td>The player of the role is: (1) a sister of the scoping person's spouse, or (2) the wife of the scoping person's brother, or (3) the wife of a brother of the scoping person's spouse.<\/td><\/tr><tr><td>SON<\/td><td>natural son<\/td><td>The player of the role is a male offspring of the scoping entity (parent).<\/td><\/tr><tr><td>SONADOPT<\/td><td>adopted son<\/td><td>The player of the role is a male child taken into a family through legal means and raised by the scoping person (parent) as his or her own child.<\/td><\/tr><tr><td>SONC<\/td><td>son<\/td><td>&lt;New Concept&gt; The player of the role is a male child (of any type) of scoping entity (parent).<\/td><\/tr><tr><td>SONFOST<\/td><td>foster son<\/td><td>The player of the role is a male child receiving parental care and nurture from the scoping person (parent) but not related to him or her through legal or blood ties.<\/td><\/tr><tr><td>SONINLAW<\/td><td>son in-law<\/td><td>The player of the role is the husband of scoping person's daughter.<\/td><\/tr><tr><td>STPBRO<\/td><td>stepbrother<\/td><td>The player of the role is a son of the scoping person's stepparent.<\/td><\/tr><tr><td>STPCHLD<\/td><td>step child<\/td><td>The player of the role is a child of the scoping person's spouse by a previous union.<\/td><\/tr><tr><td>STPDAU<\/td><td>stepdaughter<\/td><td>The player of the role is a daughter of the scoping person's spouse by a previous union.<\/td><\/tr><tr><td>STPFTH<\/td><td>stepfather<\/td><td>The player of the role is the husband of scoping person's mother and not the scoping person's natural father.<\/td><\/tr><tr><td>STPMTH<\/td><td>stepmother<\/td><td>The player of the role is the wife of scoping person's father and not the scoping person's natural mother.<\/td><\/tr><tr><td>STPPRN<\/td><td>step parent<\/td><td>The player of the role is the spouse of the scoping person's parent and not the scoping person's natural parent.<\/td><\/tr><tr><td>STPSIB<\/td><td>step sibling<\/td><td>The player of the role is a child of the scoping person's stepparent.<\/td><\/tr><tr><td>STPSIS<\/td><td>stepsister<\/td><td>The player of the role is a daughter of the scoping person's stepparent.<\/td><\/tr><tr><td>STPSON<\/td><td>stepson<\/td><td>The player of the role is a son of the scoping person's spouse by a previous union.<\/td><\/tr><tr><td>UNCLE<\/td><td>uncle<\/td><td>The player of the role is a brother of the scoping person's mother or father.<\/td><\/tr><tr><td>WIFE<\/td><td>wife<\/td><td>The player of the role is a woman joined to a man (scoping person) in marriage.<\/td><\/tr><\/table><\/li><\/ul><\/div>"},"identifier":{"value":"http://hl7.org/fhir/vs/familial-relationship"},"name":{"value":"FamilialRelationship"},"publisher":{"value":"HL7 (FHIR Project)"},"telecom":[{"system":{"value":"url"},"value":{"value":"http://hl7.org/fhir"}},{"system":{"value":"email"},"value":{"value":"fhir@lists.hl7.org"}}],"description":{"value":"The nature of the relationship between the patient and the person with the condition. Based on the HL7v3 RoleCode: OID: 2.16.840.1.113883.5.111 with some inappropriate items removed"},"status":{"value":"draft"},"date":{"value":"2023-05-12T00:10:00"},"compose":{"include":[{"system":{"value":"http://hl7.org/fhir/v3/RoleCode"},"code":[{"extension":[{"url":{"value":"http://hl7.org/fhir/tools/extensions#definition"},"valueString":{"value":"The player of the role is a sister of the scoping person's mother or father."}}],"value":"AUNT"},{"extension":[{"url":{"value":"http://hl7.org/fhir/tools/extensions#definition"},"valueString":{"value":"The player of the role is a male sharing one or both parents in common with the scoping entity."}}],"value":"BRO"},{"extension":[{"url":{"value":"http://hl7.org/fhir/tools/extensions#definition"},"valueString":{"value":"The player of the role is: (1) a brother of the scoping person's spouse, or (2) the husband of the scoping person's sister, or (3) the husband of a sister of the scoping person's spouse."}}],"value":"BROINLAW"},{"extension":[{"url":{"value":"http://hl7.org/fhir/tools/extensions#definition"},"valueString":{"value":"The player of the role is a child taken into a family through legal means and raised by the scoping person (parent) as his or her own child."}}],"value":"CHLDADOPT"},{"extension":[{"url":{"value":"http://hl7.org/fhir/tools/extensions#definition"},"valueString":{"value":"The player of the role is a child receiving parental care and nurture from the scoping person (parent) but not related to him or her through legal or blood ties."}}],"value":"CHLDFOST"},{"extension":[{"url":{"value":"http://hl7.org/fhir/tools/extensions#definition"},"valueString":{"value":"The player of the role is the spouse of scoping person's child."}}],"value":"CHLDINLAW"},{"extension":[{"url":{"value":"http://hl7.org/fhir/tools/extensions#definition"},"valueString":{"value":"The player of the role is a relative of the scoping person descended from a common ancestor, such as a grandparent, by two or more steps in a diverging line."}}],"value":"COUSN"},{"extension":[{"url":{"value":"http://hl7.org/fhir/tools/extensions#definition"},"valueString":{"value":"The player of the role is a female offspring of the scoping entity (parent)."}}],"value":"DAU"},{"extension":[{"url":{"value":"http://hl7.org/fhir/tools/extensions#definition"},"valueString":{"value":"The player of the role is a female child taken into a family through legal means and raised by the scoping person (parent) as his or her own child."}}],"value":"DAUADOPT"},{"extension":[{"url":{"value":"http://hl7.org/fhir/tools/extensions#definition"},"valueString":{"value":"<New Concept> The player of the role is a female child (of any type) of scoping entity (parent)."}}],"value":"DAUC"},{"extension":[{"url":{"value":"http://hl7.org/fhir/tools/extensions#definition"},"valueString":{"value":"The player of the role is a female child receiving parental care and nurture from the scoping person (parent) but not related to him or her through legal or blood ties."}}],"value":"DAUFOST"},{"extension":[{"url":{"value":"http://hl7.org/fhir/tools/extensions#definition"},"valueString":{"value":"The player of the role is the wife of scoping person's son."}}],"value":"DAUINLAW"},{"extension":[{"url":{"value":"http://hl7.org/fhir/tools/extensions#definition"},"valueString":{"value":"The player of the role is a child of the scoping entity."}}],"value":"CHILD"},{"extension":[{"url":{"value":"http://hl7.org/fhir/tools/extensions#definition"},"valueString":{"value":"A family member outside the immediate family unit, not having a direct genetic or legal relationship e.g. Aunt, cousin, great grandparent, grandchild, grandparent, neiceNephew, and uncle."}}],"value":"EXT"},{"extension":[{"url":{"value":"http://hl7.org/fhir/tools/extensions#definition"},"valueString":{"value":"A member of the immediate family unit by direct genetic or legal relationship."}}],"value":"IMED"},{"extension":[{"url":{"value":"http://hl7.org/fhir/tools/extensions#definition"},"valueString":{"value":"one that begets or brings forth offspring or a person who brings up and cares for another (Webster's Collegiate Dictionary)."}}],"value":"PRN"},{"extension":[{"url":{"value":"http://hl7.org/fhir/tools/extensions#definition"},"valueString":{"value":"One person who shares a parent or parents with another."}}],"value":"SIB"},{"extension":[{"url":{"value":"http://hl7.org/fhir/tools/extensions#definition"},"valueString":{"value":"A person who is important to one's well being; especially a spouse or one in a similar relationship. (The player is the one who is important)."}}],"value":"SIGOTHR"},{"extension":[{"url":{"value":"http://hl7.org/fhir/tools/extensions#definition"},"valueString":{"value":"The player of the role cohabits with the scoping person but is not the scoping person's spouse."}}],"value":"DOMPART"},{"extension":[{"url":{"value":"http://hl7.org/fhir/tools/extensions#definition"},"valueString":{"value":"The player of the role is a marriage partner of the scoping person."}}],"value":"SPS"},{"extension":[{"url":{"value":"http://hl7.org/fhir/tools/extensions#definition"},"valueString":{"value":"The player of the role is a male who begets or raises or nurtures the scoping entity (child)."}}],"value":"FTH"},{"extension":[{"url":{"value":"http://hl7.org/fhir/tools/extensions#definition"},"valueString":{"value":"The player of the role is the father of the scoping person's husband or wife."}}],"value":"FTHINLAW"},{"extension":[{"url":{"value":"http://hl7.org/fhir/tools/extensions#definition"},"valueString":{"value":"The player of the role is the father of the scoping person's grandparent."}}],"value":"GGRFTH"},{"extension":[{"url":{"value":"http://hl7.org/fhir/tools/extensions#definition"},"valueString":{"value":"The player of the role is the mother of the scoping person's grandparent."}}],"value":"GGRMTH"},{"extension":[{"url":{"value":"http://hl7.org/fhir/tools/extensions#definition"},"valueString":{"value":"The player of the role is a parent of the scoping person's grandparent."}}],"value":"GGRPRN"},{"extension":[{"url":{"value":"http://hl7.org/fhir/tools/extensions#definition"},"valueString":{"value":"The player of the role is the father of the scoping person's mother or father."}}],"value":"GRFTH"},{"extension":[{"url":{"value":"http://hl7.org/fhir/tools/extensions#definition"},"valueString":{"value":"The player of the role is the mother of the scoping person's mother or father."}}],"value":"GRMTH"},{"extension":[{"url":{"value":"http://hl7.org/fhir/tools/extensions#definition"},"valueString":{"value":"The player of the role is a child of the scoping person's son or daughter."}}],"value":"GRNDCHILD"},{"extension":[{"url":{"value":"http://hl7.org/fhir/tools/extensions#definition"},"valueString":{"value":"The player of the role is a daughter of the scoping person's son or daughter."}}],"value":"GRNDDAU"},{"extension":[{"url":{"value":"http://hl7.org/fhir/tools/extensions#definition"},"valueString":{"value":"The player of the role is a son of the scoping person's son or daughter."}}],"value":"GRNDSON"},{"extension":[{"url":{"value":"http://hl7.org/fhir/tools/extensions#definition"},"valueString":{"value":"parent of a parent of the subject."}}],"value":"GRPRN"},{"extension":[{"url":{"value":"http://hl7.org/fhir/tools/extensions#definition"},"valueString":{"value":"The player of the role is a male related to the scoping entity by sharing only one biological parent."}}],"value":"HBRO"},{"extension":[{"url":{"value":"http://hl7.org/fhir/tools/extensions#definition"},"valueString":{"value":"The player of the role is related to the scoping entity by sharing only one biological parent."}}],"value":"HSIB"},{"extension":[{"url":{"value":"http://hl7.org/fhir/tools/extensions#definition"},"valueString":{"value":"The player of the role is a female related to the scoping entity by sharing only one biological parent."}}],"value":"HSIS"},{"extension":[{"url":{"value":"http://hl7.org/fhir/tools/extensions#definition"},"valueString":{"value":"The player of the role is a man joined to a woman (scoping person) in marriage."}}],"value":"HUSB"},{"extension":[{"url":{"value":"http://hl7.org/fhir/tools/extensions#definition"},"valueString":{"value":"The player of the role is a female who conceives, gives birth to, or raises and nurtures the scoping entity (child)."}}],"value":"MTH"},{"extension":[{"url":{"value":"http://hl7.org/fhir/tools/extensions#definition"},"valueString":{"value":"The player of the role is the mother of the scoping person's husband or wife."}}],"value":"MTHINLAW"},{"extension":[{"url":{"value":"http://hl7.org/fhir/tools/extensions#definition"},"valueString":{"value":"The player of the role lives near or next to the scoping person."}}],"value":"NBOR"},{"extension":[{"url":{"value":"http://hl7.org/fhir/tools/extensions#definition"},"valueString":{"value":"The player of the role is a male having the same biological parents as the scoping entity."}}],"value":"NBRO"},{"extension":[{"url":{"value":"http://hl7.org/fhir/tools/extensions#definition"},"valueString":{"value":"A child as determined by birth."}}],"value":"NCHILD"},{"extension":[{"url":{"value":"http://hl7.org/fhir/tools/extensions#definition"},"valueString":{"value":"The player of the role is a son of the scoping person's brother or sister or of the brother or sister of the scoping person's spouse."}}],"value":"NEPHEW"},{"extension":[{"url":{"value":"http://hl7.org/fhir/tools/extensions#definition"},"valueString":{"value":"The player of the role is a male who begets the scoping entity (child)."}}],"value":"NFTH"},{"extension":[{"url":{"value":"http://hl7.org/fhir/tools/extensions#definition"},"valueString":{"value":"Indicates the biologic male parent of a fetus."}}],"value":"NFTHF"},{"extension":[{"url":{"value":"http://hl7.org/fhir/tools/extensions#definition"},"valueString":{"value":"The player of the role is a daughter of the scoping person's brother or sister or of the brother or sister of the scoping person's spouse."}}],"value":"NIECE"},{"extension":[{"url":{"value":"http://hl7.org/fhir/tools/extensions#definition"},"valueString":{"value":"The player of the role is a child of scoping person's brother or sister or of the brother or sister of the scoping person's spouse."}}],"value":"NIENEPH"},{"extension":[{"url":{"value":"http://hl7.org/fhir/tools/extensions#definition"},"valueString":{"value":"The player of the role is a female who conceives or gives birth to the scoping entity (child)."}}],"value":"NMTH"},{"extension":[{"url":{"value":"http://hl7.org/fhir/tools/extensions#definition"},"valueString":{"value":"Played by an individual who is designated as the next of kin for another individual which scopes the role."}}],"value":"NOK"},{"value":"NPRN"},{"extension":[{"url":{"value":"http://hl7.org/fhir/tools/extensions#definition"},"valueString":{"value":"The player of the role has both biological parents in common with the scoping entity."}}],"value":"NSIB"},{"extension":[{"url":{"value":"http://hl7.org/fhir/tools/extensions#definition"},"valueString":{"value":"The player of the role is a female having the same biological parents as the scoping entity."}}],"value":"NSIS"},{"extension":[{"url":{"value":"http://hl7.org/fhir/tools/extensions#definition"},"valueString":{"value":"The player of the role is the parent of scoping person's husband or wife."}}],"value":"PRNINLAW"},{"extension":[{"url":{"value":"http://hl7.org/fhir/tools/extensions#definition"},"valueString":{"value":"One who shares living quarters with the subject."}}],"value":"ROOM"},{"extension":[{"url":{"value":"http://hl7.org/fhir/tools/extensions#definition"},"valueString":{"value":"The player of the role is: (1) a sibling of the scoping person's spouse, or (2) the spouse of the scoping person's sibling, or (3) the spouse of a sibling of the scoping person's spouse."}}],"value":"SIBINLAW"},{"extension":[{"url":{"value":"http://hl7.org/fhir/tools/extensions#definition"},"valueString":{"value":"The player of the role is a female sharing one or both parents in common with the scoping entity."}}],"value":"SIS"},{"extension":[{"url":{"value":"http://hl7.org/fhir/tools/extensions#definition"},"valueString":{"value":"The player of the role is: (1) a sister of the scoping person's spouse, or (2) the wife of the scoping person's brother, or (3) the wife of a brother of the scoping person's spouse."}}],"value":"SISINLAW"},{"extension":[{"url":{"value":"http://hl7.org/fhir/tools/extensions#definition"},"valueString":{"value":"The player of the role is a male offspring of the scoping entity (parent)."}}],"value":"SON"},{"extension":[{"url":{"value":"http://hl7.org/fhir/tools/extensions#definition"},"valueString":{"value":"The player of the role is a male child taken into a family through legal means and raised by the scoping person (parent) as his or her own child."}}],"value":"SONADOPT"},{"extension":[{"url":{"value":"http://hl7.org/fhir/tools/extensions#definition"},"valueString":{"value":"<New Concept> The player of the role is a male child (of any type) of scoping entity (parent)."}}],"value":"SONC"},{"extension":[{"url":{"value":"http://hl7.org/fhir/tools/extensions#definition"},"valueString":{"value":"The player of the role is a male child receiving parental care and nurture from the scoping person (parent) but not related to him or her through legal or blood ties."}}],"value":"SONFOST"},{"extension":[{"url":{"value":"http://hl7.org/fhir/tools/extensions#definition"},"valueString":{"value":"The player of the role is the husband of scoping person's daughter."}}],"value":"SONINLAW"},{"extension":[{"url":{"value":"http://hl7.org/fhir/tools/extensions#definition"},"valueString":{"value":"The player of the role is a son of the scoping person's stepparent."}}],"value":"STPBRO"},{"extension":[{"url":{"value":"http://hl7.org/fhir/tools/extensions#definition"},"valueString":{"value":"The player of the role is a child of the scoping person's spouse by a previous union."}}],"value":"STPCHLD"},{"extension":[{"url":{"value":"http://hl7.org/fhir/tools/extensions#definition"},"valueString":{"value":"The player of the role is a daughter of the scoping person's spouse by a previous union."}}],"value":"STPDAU"},{"extension":[{"url":{"value":"http://hl7.org/fhir/tools/extensions#definition"},"valueString":{"value":"The player of the role is the husband of scoping person's mother and not the scoping person's natural father."}}],"value":"STPFTH"},{"extension":[{"url":{"value":"http://hl7.org/fhir/tools/extensions#definition"},"valueString":{"value":"The player of the role is the wife of scoping person's father and not the scoping person's natural mother."}}],"value":"STPMTH"},{"extension":[{"url":{"value":"http://hl7.org/fhir/tools/extensions#definition"},"valueString":{"value":"The player of the role is the spouse of the scoping person's parent and not the scoping person's natural parent."}}],"value":"STPPRN"},{"extension":[{"url":{"value":"http://hl7.org/fhir/tools/extensions#definition"},"valueString":{"value":"The player of the role is a child of the scoping person's stepparent."}}],"value":"STPSIB"},{"extension":[{"url":{"value":"http://hl7.org/fhir/tools/extensions#definition"},"valueString":{"value":"The player of the role is a daughter of the scoping person's stepparent."}}],"value":"STPSIS"},{"extension":[{"url":{"value":"http://hl7.org/fhir/tools/extensions#definition"},"valueString":{"value":"The player of the role is a son of the scoping person's spouse by a previous union."}}],"value":"STPSON"},{"extension":[{"url":{"value":"http://hl7.org/fhir/tools/extensions#definition"},"valueString":{"value":"The player of the role is a brother of the scoping person's mother or father."}}],"value":"UNCLE"},{"extension":[{"url":{"value":"http://hl7.org/fhir/tools/extensions#definition"},"valueString":{"value":"The player of the role is a woman joined to a man (scoping person) in marriage."}}],"value":"WIFE"}]}]}}}